palpageproducer/__init__.py
palpageproducer/__main__.py
palpageproducer-1.3.0.dist-info/AUTHORS
palpageproducer-1.3.0.dist-info/LICENSE
palpageproducer-1.3.0.dist-info/METADATA
palpageproducer-1.3.0.dist-info/WHEEL
palpageproducer-1.3.0.dist-info/entry_points.txt
palpageproducer-1.3.0.dist-info/top_level.txt
palpageproducer-1.3.0.dist-info/RECORD
