Metadata-Version: 2.1
Name: palpageproducer
Version: 1.3.0
Summary: Palette page producer
Home-page: https://www.twinkle-night.net/Code/ppp.html
Author: Garrick
Author-email: earthisthering@posteo.de
License: GPLv3+
Keywords: sass html colors
Platform: UNKNOWN
Classifier: Development Status :: 4 - Beta
Classifier: License :: OSI Approved :: GNU General Public License v3 or later (GPLv3+)
Classifier: Programming Language :: Python :: 3
Classifier: Intended Audience :: End Users/Desktop
Classifier: Topic :: Multimedia :: Graphics
Classifier: Topic :: Multimedia :: Graphics :: Graphics Conversion
Requires-Dist: appdirs
Requires-Dist: python-slugify
